grafana_wtf/__init__.py
grafana_wtf/commands.py
grafana_wtf/compat.py
grafana_wtf/core.py
grafana_wtf/model.py
grafana_wtf/util.py
grafana_wtf/report/__init__.py
grafana_wtf/report/data.py
grafana_wtf/report/tabular.py
grafana_wtf/report/textual.py
grafana_wtf-0.23.5.dist-info/licenses/LICENSE
grafana_wtf-0.23.5.dist-info/METADATA
grafana_wtf-0.23.5.dist-info/WHEEL
grafana_wtf-0.23.5.dist-info/entry_points.txt
grafana_wtf-0.23.5.dist-info/top_level.txt
grafana_wtf-0.23.5.dist-info/RECORD
