Metadata-Version: 2.4
Name: grafana-wtf
Version: 0.23.5
Summary: Grep through all Grafana entities in the spirit of git-wtf
Home-page: https://github.com/grafana-toolbox/grafana-wtf
Author: Andreas Motl
Author-email: andreas.motl@panodata.org
License: AGPL 3, EUPL 1.2
Keywords: grafana search index
Classifier: Programming Language :: Python
Classifier: License :: OSI Approved :: GNU Affero General Public License v3
Classifier: License :: OSI Approved :: European Union Public Licence 1.2 (EUPL 1.2)
Classifier: Development Status :: 4 - Beta
Classifier: Environment :: Console
Classifier: Intended Audience :: Developers
Classifier: Intended Audience :: Education
Classifier: Intended Audience :: Information Technology
Classifier: Intended Audience :: Manufacturing
Classifier: Intended Audience :: Science/Research
Classifier: Intended Audience :: System Administrators
Classifier: Intended Audience :: Telecommunications Industry
Classifier: Operating System :: POSIX
Classifier: Operating System :: Unix
Classifier: Operating System :: MacOS
Classifier: Programming Language :: Python
Classifier: Programming Language :: Python :: 3.8
Classifier: Programming Language :: Python :: 3.9
Classifier: Programming Language :: Python :: 3.10
Classifier: Programming Language :: Python :: 3.11
Classifier: Programming Language :: Python :: 3.12
Classifier: Programming Language :: Python :: 3.13
Classifier: Programming Language :: Python :: 3.14
Classifier: Topic :: Communications
Classifier: Topic :: Database
Classifier: Topic :: Internet
Classifier: Topic :: Scientific/Engineering :: Information Analysis
Classifier: Topic :: Scientific/Engineering :: Interface Engine/Protocol Translator
Classifier: Topic :: Scientific/Engineering :: Visualization
Classifier: Topic :: Software Development :: Embedded Systems
Classifier: Topic :: Software Development :: Libraries
Classifier: Topic :: System :: Archiving
Classifier: Topic :: System :: Networking :: Monitoring
License-File: LICENSE
Requires-Dist: six
Requires-Dist: docopt-ng<0.10,>=0.6.2
Requires-Dist: importlib-metadata; python_version < "3.8"
Requires-Dist: munch<5,>=2.5.0
Requires-Dist: tqdm<5,>=4.60.0
Requires-Dist: verlib2<0.4,>=0.3.1
Requires-Dist: pandas<2.4; platform_system != "Linux" or (platform_machine != "armv7l" and platform_machine != "aarch64")
Requires-Dist: duckdb<1.5; platform_system != "Linux" or (platform_machine != "armv7l" and platform_machine != "aarch64")
Requires-Dist: grafana-client<6,>=4
Requires-Dist: jsonpath-rw<2,>=1.4.0
Requires-Dist: requests-cache<2,>=0.8.0
Requires-Dist: tabulate<0.10,>=0.8.5
Requires-Dist: colored<3,>=1.4.3
Requires-Dist: Pygments<3,>=2.15.1
Requires-Dist: PyYAML<7,>=5
Provides-Extra: test
Requires-Dist: pytest<9; extra == "test"
Requires-Dist: pytest-cov<7; extra == "test"
Requires-Dist: lovely-pytest-docker<2,>=1; extra == "test"
Requires-Dist: grafanalib==0.7.1; extra == "test"
Dynamic: author
Dynamic: author-email
Dynamic: classifier
Dynamic: description
Dynamic: home-page
Dynamic: keywords
Dynamic: license
Dynamic: license-file
Dynamic: provides-extra
Dynamic: requires-dist
Dynamic: summary
